pysunnoaa/__init__.py
pysunnoaa/cli.py
pysunnoaa/noaa.py
pysunnoaa/pysunnoaa.py
pysunnoaa-0.1.8.dist-info/LICENSE
pysunnoaa-0.1.8.dist-info/METADATA
pysunnoaa-0.1.8.dist-info/WHEEL
pysunnoaa-0.1.8.dist-info/RECORD
