Metadata-Version: 2.1
Name: pysunnoaa
Version: 0.1.8
Summary: python implementation of NOAA's Solar Position Calculators
License: Mozilla Public License, v. 2.0
Author: Santosh Philip
Author-email: santosh@noemail.com
Requires-Python: >=3.7,<4.0
Classifier: License :: Other/Proprietary License
Classifier: Programming Language :: Python :: 3
Classifier: Programming Language :: Python :: 3.7
Classifier: Programming Language :: Python :: 3.8
Classifier: Programming Language :: Python :: 3.9
Classifier: Programming Language :: Python :: 3.10
Classifier: Programming Language :: Python :: 3.11
Classifier: Programming Language :: Python :: 3.12
Requires-Dist: julian (>=0.14,<0.15)
